{
  "type": "Feature",
  "stac_version": "1.0.0",
  "stac_extensions": [
    "https://stac-extensions.github.io/label/v1.0.1/schema.json",
    "https://raw.githubusercontent.com/earthpulse/ml-dataset/main/json-schema/schema.json"
  ],
  "id": "ship_247353700_2022-08-12",
  "geometry": {
    "type": "Polygon",
    "coordinates": [
      [
        [
          10.137885545388182,
          54.32035938392791
        ],
        [
          10.137885545388182,
          54.33167376871323
        ],
        [
          10.15788319839166,
          54.33167376871323
        ],
        [
          10.15788319839166,
          54.32035938392791
        ],
        [
          10.137885545388182,
          54.32035938392791
        ]
      ]
    ]
  },
  "bbox": [
    10.137885545388182,
    54.32035938392791,
    10.15788319839166,
    54.33167376871323
  ],
  "properties": {
    "label:classes": [
      {
        "classes": [
          "Boat"
        ],
        "name": "label"
      }
    ],
    "label:description": "Item label",
    "label:type": "raster",
    "label:properties": [
      "label"
    ],
    "label:methods": [
      "automated"
    ],
    "label:tasks": [
      "segmentation"
    ],
    "datetime": "2022-08-12T00:00:00Z",
    "ml-dataset:split": "Training"
  },
  "links": [
    {
      "rel": "source",
      "href": "../../sentinel-2-ships/ship_247353700_2022-08-12/ship_247353700_2022-08-12.json",
      "type": "application/json"
    },
    {
      "rel": "root",
      "href": "/home/pcoquard/git/eotdl/tutorials/usecases/useCaseD/data/sentinel_2_q2/catalog.json",
      "type": "application/json"
    },
    {
      "rel": "collection",
      "href": "../collection.json",
      "type": "application/json"
    },
    {
      "rel": "self",
      "href": "/home/pcoquard/git/eotdl/tutorials/usecases/useCaseD/data/sentinel_2_q2/labels/ship_247353700_2022-08-12/ship_247353700_2022-08-12.json",
      "type": "application/json"
    },
    {
      "rel": "parent",
      "href": "/home/pcoquard/git/eotdl/tutorials/usecases/useCaseD/data/sentinel_2_q2/labels/collection.json",
      "type": "application/json"
    }
  ],
  "assets": {
    "labels": {
      "href": "../../../sentinel_2/ship_247353700_2022-08-12_labels.geojson",
      "type": "application/geo+json",
      "title": "Label",
      "roles": [
        "labels",
        "labels-raster"
      ]
    }
  },
  "collection": "labels"
}