{
  "type": "Feature",
  "stac_version": "1.0.0",
  "id": "Pasture_1002",
  "properties": {
    "datetime": "2000-01-01T00:00:00Z"
  },
  "geometry": {
    "type": "Polygon",
    "coordinates": [
      [
        [
          -6.674633732563668,
          52.96982484756661
        ],
        [
          -6.674633732563668,
          52.97576314314539
        ],
        [
          -6.664808527885999,
          52.97576314314539
        ],
        [
          -6.664808527885999,
          52.96982484756661
        ],
        [
          -6.674633732563668,
          52.96982484756661
        ]
      ]
    ]
  },
  "links": [
    {
      "rel": "root",
      "href": "../../catalog.json",
      "type": "application/json"
    },
    {
      "rel": "collection",
      "href": "../collection.json",
      "type": "application/json"
    },
    {
      "rel": "parent",
      "href": "../collection.json",
      "type": "application/json"
    }
  ],
  "assets": {
    "Pasture_1002": {
      "href": "../../../EuroSAT-small/Pasture/Pasture_1002.tif",
      "type": "image/tiff; application=geotiff",
      "title": "Pasture_1002",
      "roles": [
        "data"
      ]
    }
  },
  "bbox": [
    -6.674633732563668,
    52.96982484756661,
    -6.664808527885999,
    52.97576314314539
  ],
  "stac_extensions": [],
  "collection": "source"
}