{
  "type": "Feature",
  "stac_version": "1.0.0",
  "id": "SeaLake_1002",
  "properties": {
    "datetime": "2000-01-01T00:00:00Z"
  },
  "geometry": {
    "type": "Polygon",
    "coordinates": [
      [
        [
          0.5115835939355594,
          51.656690370946805
        ],
        [
          0.5115835939355594,
          51.66262703814245
        ],
        [
          0.5211543915863706,
          51.66262703814245
        ],
        [
          0.5211543915863706,
          51.656690370946805
        ],
        [
          0.5115835939355594,
          51.656690370946805
        ]
      ]
    ]
  },
  "links": [
    {
      "rel": "root",
      "href": "../../catalog.json",
      "type": "application/json"
    },
    {
      "rel": "collection",
      "href": "../collection.json",
      "type": "application/json"
    },
    {
      "rel": "parent",
      "href": "../collection.json",
      "type": "application/json"
    }
  ],
  "assets": {
    "SeaLake_1002": {
      "href": "../../../EuroSAT-small/SeaLake/SeaLake_1002.tif",
      "type": "image/tiff; application=geotiff",
      "title": "SeaLake_1002",
      "roles": [
        "data"
      ]
    }
  },
  "bbox": [
    0.5115835939355594,
    51.656690370946805,
    0.5211543915863706,
    51.66262703814245
  ],
  "stac_extensions": [],
  "collection": "source"
}