{
  "type": "Feature",
  "stac_version": "1.0.0",
  "id": "Residential_2704",
  "properties": {
    "datetime": "2000-01-01T00:00:00Z"
  },
  "geometry": {
    "type": "Polygon",
    "coordinates": [
      [
        [
          0.0,
          0.0
        ],
        [
          0.0,
          0.0
        ],
        [
          0.0,
          0.0
        ],
        [
          0.0,
          0.0
        ]
      ]
    ]
  },
  "links": [
    {
      "rel": "root",
      "href": "../../catalog.json",
      "type": "application/json"
    },
    {
      "rel": "collection",
      "href": "../collection.json",
      "type": "application/json"
    },
    {
      "rel": "parent",
      "href": "../collection.json",
      "type": "application/json"
    }
  ],
  "assets": {
    "Residential_2704": {
      "href": "../../../EuroSAT-RGB-small/Residential/Residential_2704.jpg",
      "type": "image/jpeg",
      "title": "Residential_2704",
      "roles": [
        "data"
      ]
    }
  },
  "bbox": [
    0,
    0,
    0,
    0
  ],
  "stac_extensions": [],
  "collection": "source"
}